pybicyclewheel/__init__.py
pybicyclewheel/dataloader.py
pybicyclewheel/hub.py
pybicyclewheel/rim.py
pybicyclewheel/wheel.py
pybicyclewheel/xls_calc.py
pybicyclewheel_gui/__init__.py
pybicyclewheel_gui/__main__.py
pybicyclewheel_gui/tile/__init__.py
pybicyclewheel_gui/tile/core.py
pybicyclewheel-0.0.9.dist-info/LICENSE.md
pybicyclewheel-0.0.9.dist-info/METADATA
pybicyclewheel-0.0.9.dist-info/WHEEL
pybicyclewheel-0.0.9.dist-info/top_level.txt
pybicyclewheel-0.0.9.dist-info/RECORD
