Metadata-Version: 2.1
Name: pybicyclewheel
Version: 0.0.9
Summary: pybicyclewheel - bicycle spoke length calculator
Home-page: https://github.com/kr-g/pybicyclewheel
Author: k. goger
Author-email: k.r.goger+pybicyclewheel@gmail.com
License: UNKNOWN
Keywords: bicycle spoke length calculator
Platform: UNKNOWN
Classifier: Development Status :: 3 - Alpha
Classifier: Operating System :: POSIX :: Linux
Classifier: Intended Audience :: Developers
Classifier: Programming Language :: Python :: 3
Classifier: License :: OSI Approved :: GNU Affero General Public License v3 or later (AGPLv3+)
Requires-Python: >=3.8
License-File: LICENSE.md
Requires-Dist: numpy
Requires-Dist: pandas
Requires-Dist: tk
Requires-Dist: xlrd
